shopify_app_billing/__init__.py
shopify_app_billing/admin.py
shopify_app_billing/apps.py
shopify_app_billing/tests.py
shopify_app_billing/urls.py
shopify_app_billing/views.py
shopify_app_billing/migrations/0001_initial.py
shopify_app_billing/migrations/__init__.py
shopify_app_billing/models/__init__.py
shopify_app_billing/models/recurring_application_charges.py
shopify_app_billing/models/shop_billing.py
shopify_app_billing/services/__init__.py
shopify_app_billing/templates/__init__.py
django_shopify_app_billing-0.0.6.dist-info/LICENSE
django_shopify_app_billing-0.0.6.dist-info/METADATA
django_shopify_app_billing-0.0.6.dist-info/WHEEL
django_shopify_app_billing-0.0.6.dist-info/top_level.txt
django_shopify_app_billing-0.0.6.dist-info/RECORD
